connect_four_lib/__init__.py
connect_four_lib/config.py
connect_four_lib/connect_four_engine.py
connect_four_lib/connect_four_heuristic.py
connect_four_lib/connect_four_judge.py
connect_four_lib/connect_four_player.py
connect_four_lib/point.py
connect_four_lib/utils/speed.py
connect_four_lib-1.3.1.dist-info/METADATA
connect_four_lib-1.3.1.dist-info/WHEEL
connect_four_lib-1.3.1.dist-info/RECORD
