Metadata-Version: 2.1
Name: connect-four-lib
Version: 1.3.1
Summary: A library for connect 4 game
Author: game-ai-platform-team
Requires-Python: >=3.10,<4.0
Classifier: Programming Language :: Python :: 3
Classifier: Programming Language :: Python :: 3.10
Classifier: Programming Language :: Python :: 3.11
Classifier: Programming Language :: Python :: 3.12
Requires-Dist: duo-game-lib (>=0.1.0,<0.2.0)
